xtt/_ffi.abi3.so
xtt/client.py
xtt/socket.py
xtt/exceptions.py
xtt/server.py
xtt/__init__.py
xtt/certificates.py
xtt/_ffi_utils.py
xtt/_utils.py
xtt/asn1.py
xtt/crypto/lrsw.py
xtt/crypto/ecdsap256.py
xtt/crypto/__init__.py
xtt/test/certificate_test.py
xtt/test/context_test.py
xtt/test/__init__.py
xtt/test/xtt_test.py
xtt/test/asn1_test.py
xtt-0.10.0.post0.dist-info/LICENSE.txt
xtt-0.10.0.post0.dist-info/WHEEL
xtt-0.10.0.post0.dist-info/top_level.txt
xtt-0.10.0.post0.dist-info/METADATA
xtt-0.10.0.post0.dist-info/RECORD
